{
  "891bf059cbaf55574044add1afc56e2e778e464f65a77101d710879d1dea810b": {
    "rotation_matrix": [
      [
        6.123233995736766e-17,
        1.0,
        0.0
      ],
      [
        -1.0,
        6.123233995736766e-17,
        0.0
      ],
      [
        0.0,
        0.0,
        1.0
      ]
    ],
    "is_identity": false,
    "matrix_determinant": 1.0,
    "description": "Applied rotation matrix",
    "label": [
      "satellite"
    ]
  },
  "3cf863d17ccdb28189493193785767b7a3d1537dc7fbbfcd14af9bfdf11e639d": {
    "rotation_matrix": [
      [
        1.0,
        1.9967346175427393e-16,
        0.0
      ],
      [
        -1.7938038903913487e-16,
        1.0,
        0.0
      ],
      [
        0.0,
        0.0,
        1.0
      ]
    ],
    "is_identity": true,
    "matrix_determinant": 1.0,
    "description": "Identity matrix (no rotation)",
    "label": [
      "satellite"
    ]
  },
  "5c35c57af7c3aa334df7fd353a1a7844c9a5890b2e4e6858fee5605b6741b3c6": {
    "rotation_matrix": [
      [
        -1.0,
        -1.2246467991473532e-16,
        0.0
      ],
      [
        1.2246467991473532e-16,
        -1.0,
        0.0
      ],
      [
        0.0,
        0.0,
        1.0
      ]
    ],
    "is_identity": false,
    "matrix_determinant": 1.0,
    "description": "Applied rotation matrix",
    "label": [
      "satellite"
    ]
  },
  "875fd968b4de3345cfa7c3622e0ae7e322d1160934bd1ff11d88c1c407de0321": {
    "rotation_matrix": [
      [
        -1.9967346175427393e-16,
        -2.744748180560856e-32,
        1.0
      ],
      [
        1.2246467991473532e-16,
        -1.0,
        0.0
      ],
      [
        1.0,
        1.2246467991473532e-16,
        1.7938038903913487e-16
      ]
    ],
    "is_identity": false,
    "matrix_determinant": 1.0,
    "description": "Applied rotation matrix",
    "label": [
      "satellite"
    ]
  },
  "99113d081d62724e51437b82c18e9735d2e0df83536920475937d08ffaff493e": {
    "rotation_matrix": [
      [
        6.123233995736766e-17,
        1.0,
        0.0
      ],
      [
        -1.0,
        6.123233995736766e-17,
        0.0
      ],
      [
        0.0,
        0.0,
        1.0
      ]
    ],
    "is_identity": false,
    "matrix_determinant": 1.0,
    "description": "Applied rotation matrix",
    "label": [
      "satellite"
    ]
  },
  "bd64ab46506e38a442f2115af7d61e19f510e32ef2a7d267a632afcc180f3f3a": {
    "rotation_matrix": [
      [
        6.123233995736766e-17,
        -1.0,
        0.0
      ],
      [
        1.0,
        6.123233995736766e-17,
        0.0
      ],
      [
        0.0,
        0.0,
        1.0
      ]
    ],
    "is_identity": false,
    "matrix_determinant": 1.0,
    "description": "Applied rotation matrix",
    "label": [
      "satellite"
    ]
  },
  "ad954d50f1952fef89f37d24d725d3bd5fc531b4e990e01014e8defc8ea50778": {
    "rotation_matrix": [
      [
        1.9967346175427393e-16,
        -1.0,
        0.0
      ],
      [
        1.0,
        1.7938038903913487e-16,
        0.0
      ],
      [
        0.0,
        0.0,
        1.0
      ]
    ],
    "is_identity": false,
    "matrix_determinant": 1.0,
    "description": "Applied rotation matrix",
    "label": [
      "satellite"
    ]
  },
  "5b3ca11b1feb6c3b6810e6e6aeb0b1353114a51bd82208b21da2a3f57cd64d68": {
    "rotation_matrix": [
      [
        6.123233995736766e-17,
        -1.0,
        0.0
      ],
      [
        1.0,
        6.123233995736766e-17,
        0.0
      ],
      [
        0.0,
        0.0,
        1.0
      ]
    ],
    "is_identity": false,
    "matrix_determinant": 1.0,
    "description": "Applied rotation matrix",
    "label": [
      "satellite"
    ]
  },
  "de6b81b2c020fff2bda0b5073713751702440a0d06421880fce1496219b3f63e": {
    "rotation_matrix": [
      [
        6.123233995736766e-17,
        -1.0,
        0.0
      ],
      [
        1.0,
        6.123233995736766e-17,
        0.0
      ],
      [
        0.0,
        0.0,
        1.0
      ]
    ],
    "is_identity": false,
    "matrix_determinant": 1.0,
    "description": "Applied rotation matrix",
    "label": [
      "satellite"
    ]
  },
  "2e1d0e4f3f96d0064edb05321fa7f27002e73e368699e98f443a60114ab56e79": {
    "rotation_matrix": [
      [
        6.123233995736766e-17,
        -1.0,
        0.0
      ],
      [
        1.0,
        6.123233995736766e-17,
        0.0
      ],
      [
        0.0,
        0.0,
        1.0
      ]
    ],
    "is_identity": false,
    "matrix_determinant": 1.0,
    "description": "Applied rotation matrix",
    "label": [
      "satellite"
    ]
  },
  "171bb0dcaf5b237a430610c97b5d68400e5295e3e9f20eb14befc24066d0e229": {
    "rotation_matrix": [
      [
        6.123233995736766e-17,
        -1.0,
        0.0
      ],
      [
        1.0,
        6.123233995736766e-17,
        0.0
      ],
      [
        0.0,
        0.0,
        1.0
      ]
    ],
    "is_identity": false,
    "matrix_determinant": 1.0,
    "description": "Applied rotation matrix",
    "label": [
      "satellite"
    ]
  }
}